setup.py
kedro_graphql/__init__.py
kedro_graphql/__main__.py
kedro_graphql/asgi.py
kedro_graphql/celeryapp.py
kedro_graphql/client.py
kedro_graphql/commands.py
kedro_graphql/config.py
kedro_graphql/decorators.py
kedro_graphql/exceptions.py
kedro_graphql/hooks.py
kedro_graphql/models.py
kedro_graphql/permissions.py
kedro_graphql/pipeline_event_monitor.py
kedro_graphql/pipeline_registry.py
kedro_graphql/schema.py
kedro_graphql/settings.py
kedro_graphql/tasks.py
kedro_graphql/utils.py
kedro_graphql/backends/__init__.py
kedro_graphql/backends/base.py
kedro_graphql/backends/mongodb.py
kedro_graphql/example/__init__.py
kedro_graphql/example/app.py
kedro_graphql/logs/__init__.py
kedro_graphql/logs/json_log_formatter.py
kedro_graphql/logs/logger.py
kedro_graphql/pipelines/__init__.py
kedro_graphql/pipelines/event00/__init__.py
kedro_graphql/pipelines/event00/nodes.py
kedro_graphql/pipelines/event00/pipeline.py
kedro_graphql/pipelines/example00/__init__.py
kedro_graphql/pipelines/example00/nodes.py
kedro_graphql/pipelines/example00/pipeline.py
kedro_graphql/pipelines/example01/__init__.py
kedro_graphql/pipelines/example01/nodes.py
kedro_graphql/pipelines/example01/pipeline.py
kedro_graphql/plugins/__init__.py
kedro_graphql/plugins/plugins.py
kedro_graphql/runners/__init__.py
kedro_graphql/runners/argo/__init__.py
kedro_graphql/runners/argo/argo.py
kedro_graphql/signed_url/__init__.py
kedro_graphql/signed_url/base.py
kedro_graphql/signed_url/local_file_provider.py
kedro_graphql/signed_url/s3_provider.py
kedro_graphql/static/queries.gql
kedro_graphql/ui/__init__.py
kedro_graphql/ui/app.py
kedro_graphql/ui/auth.py
kedro_graphql/ui/decorators.py
kedro_graphql/ui/plugins.py
kedro_graphql/ui/components/__init__.py
kedro_graphql/ui/components/data_catalog_explorer.py
kedro_graphql/ui/components/dataset_perspective.py
kedro_graphql/ui/components/pipeline_cards.py
kedro_graphql/ui/components/pipeline_cloning.py
kedro_graphql/ui/components/pipeline_dashboard_factory.py
kedro_graphql-1.3.1.dist-info/licenses/LICENSE.txt
kedro_graphql-1.3.1.dist-info/METADATA
kedro_graphql-1.3.1.dist-info/WHEEL
kedro_graphql-1.3.1.dist-info/entry_points.txt
kedro_graphql-1.3.1.dist-info/top_level.txt
kedro_graphql-1.3.1.dist-info/RECORD
