Metadata-Version: 2.4
Name: kedro-graphql
Version: 1.3.1
Summary: A kedro plugin for serving any kedro project as a GraphQL api
Author: opensean
License: MIT
Project-URL: Homepage, https://github.com/opensean/kedro-graphql
Project-URL: Source, https://github.com/opensean/kedro-graphql
Keywords: pipelines,machine learning,data pipelines,data science,data engineering,graphql
Classifier: Programming Language :: Python :: 3.10
Classifier: Programming Language :: Python :: 3.11
Requires-Python: <3.12,>=3.10
License-File: LICENSE.txt
Requires-Dist: kedro==0.19.11
Requires-Dist: kedro-datasets>=3.0.0
Requires-Dist: fastapi>=0.115.11
Requires-Dist: pymongo>=4.7.2
Requires-Dist: python-dotenv>=1.0.1
Requires-Dist: gql[all]<4,>=3.5.1
Requires-Dist: strawberry-graphql>=0.262.5
Requires-Dist: uvicorn[standard]>=0.30.0
Requires-Dist: redis>=5.0.0
Requires-Dist: click>=4.0
Requires-Dist: celery>=5.4.0
Requires-Dist: boto3>=1.26.160
Requires-Dist: asyncio>=3.4.3
Requires-Dist: cloudevents
Requires-Dist: PyJWT>=2.10.1
Requires-Dist: python-multipart>=0.0.20
Provides-Extra: test
Requires-Dist: pandas>=2.2.0; extra == "test"
Requires-Dist: pytest-cov<7,>=3; extra == "test"
Requires-Dist: pytest-mock<4.0,>=1.7.1; extra == "test"
Requires-Dist: pytest<9.0,>=7.2; extra == "test"
Requires-Dist: pytest-asyncio>=0.23.7; extra == "test"
Requires-Dist: celery[pytest]~=5.4.0; extra == "test"
Requires-Dist: pydoc-markdown; extra == "test"
Requires-Dist: mkdocs; extra == "test"
Requires-Dist: mkdocstrings[python]; extra == "test"
Requires-Dist: mkdocs-material; extra == "test"
Provides-Extra: experimental
Requires-Dist: minio~=7.1.15; extra == "experimental"
Provides-Extra: ui
Requires-Dist: panel>=1.6.1; extra == "ui"
Requires-Dist: kedro-viz>=10.2.0; extra == "ui"
Requires-Dist: sh>=2.2.2; extra == "ui"
Dynamic: license-file
